LICENSE
MANIFEST.in
README.rst
setup.cfg
setup.py
pycli_tools/__init__.py
pycli_tools/actions.py
pycli_tools/commands.py
pycli_tools/parsers.py
pycli_tools/rawinput.py
pycli_tools.egg-info/PKG-INFO
pycli_tools.egg-info/SOURCES.txt
pycli_tools.egg-info/dependency_links.txt
pycli_tools.egg-info/not-zip-safe
pycli_tools.egg-info/top_level.txt
test/test_actions.py
test/test_ask_user_yesno.py
test/test_getargparser.py