Metadata-Version: 1.1
Name: pycli-tools
Version: 2.0.1
Summary: A python module to help create predictable command line tools for python >= 2.6 and 3.x
Home-page: http://nrocco.github.io/
Author: Nico Di Rocco
Author-email: dirocco.nico@gmail.com
License: GPLv3
Download-URL: http://github.com/nrocco/pycli-tools
Platform: UNKNOWN
Classifier: Operating System :: OS Independent
Classifier: Development Status :: 5 - Production/Stable
Classifier: Environment :: Console
Classifier: License :: OSI Approved :: GNU General Public License v3 (GPLv3)
Classifier: Operating System :: Unix
Classifier: Programming Language :: Python
Classifier: Programming Language :: Python :: 2
Classifier: Programming Language :: Python :: 2.6
Classifier: Programming Language :: Python :: 2.7
Classifier: Programming Language :: Python :: 3
Classifier: Programming Language :: Python :: 3.0
Classifier: Programming Language :: Python :: 3.1
Classifier: Programming Language :: Python :: 3.2
Classifier: Programming Language :: Python :: 3.3
Classifier: Topic :: Software Development :: Libraries :: Python Modules
